rl_helpers/__init__.py
rl_helpers/py.typed
rl_helpers/supervised_learning.py
rl_helpers-0.8.5.dist-info/WHEEL
rl_helpers-0.8.5.dist-info/METADATA
rl_helpers-0.8.5.dist-info/RECORD
