Metadata-Version: 2.3
Name: rl-helpers
Version: 0.8.5
Summary: Helper functions mostly for training RL agents but also for some supervised learning.
Author: Valter Schütz
Author-email: Valter Schütz <valterschutz@proton.me>
Requires-Dist: lightning>=2.6.0
Requires-Dist: torchrl>=0.9.2
Requires-Python: >=3.11
